{
	"name": "SlimeKing",
	"plugin-id": "Sprite",
	"sid": 947794935422554,
	"isGlobal": false,
	"instanceVariables": [],
	"behaviorTypes": [
		{
			"behaviorId": "Tween",
			"name": "Tween",
			"sid": 776019594967398
		}
	],
	"effectTypes": [],
	"animations": {
		"items": [
			{
				"frames": [
					{
						"width": 30,
						"height": 29,
						"originX": 0.5333333333333333,
						"originY": 0.6551724137931034,
						"originalSource": "",
						"exportFormat": "png",
						"exportQuality": 0.8,
						"imageSpriteId": 4935654,
						"collisionPoly": {
							"points": [
								0.03333333333333333,
								0,
								1,
								0,
								1,
								0,
								1,
								0,
								1,
								1,
								0.03333333333333333,
								1
							]
						},
						"useCollisionPoly": true,
						"duration": 1
					}
				],
				"sid": 273485200261472,
				"name": "Animation 1",
				"isLooping": false,
				"isPingPong": false,
				"repeatCount": 1,
				"repeatTo": 0,
				"speed": 5
			}
		],
		"subfolders": []
	}
}